lightweight_orchestration/__init__.py
lightweight_orchestration/simple_batch_orchestration.py
lightweight_orchestration/simple_job_orchestration.py
tests/__init__.py
tests/manual_test_simple_batch_orchestration.py
tests/manual_test_simple_job_orchestration.py
tests/test_simple_job_orchestration.py
lightweight_orchestration-0.1.0.dist-info/LICENSE
lightweight_orchestration-0.1.0.dist-info/METADATA
lightweight_orchestration-0.1.0.dist-info/WHEEL
lightweight_orchestration-0.1.0.dist-info/top_level.txt
lightweight_orchestration-0.1.0.dist-info/RECORD
