Metadata-Version: 2.1
Name: lightweight_orchestration
Version: 0.1.0
Summary: Lightweight orchestration processes for intelligence jobs in Python.
Home-page: https://github.com/Proactive-Ingredient/lightweight_orchestration.git
Author: Carlos Miranda Durand
Author-email: carlosm@proactiveingredient.com
License: AGPL-3.0-or-later
Classifier: Programming Language :: Python :: 3
Classifier: License :: OSI Approved :: GNU Affero General Public License v3 or later (AGPLv3+)
Classifier: Operating System :: OS Independent
Requires-Python: >=3.10
License-File: LICENSE
